{"name":"Django-realtime-validation","tagline":"Django client-side realtime form validation using JavaScript","body":"django-realtime-validation\r\n==========================\r\n\r\nDjango client-side realtime form field validation using JavaScript.\r\n\r\nThis **does not use AJAX** or any other server communcation to validate the form fields, so there are no extra requests being made to the server.\r\n\r\nUsage\r\n-----\r\n\r\n*settings.py*\r\n\r\n    INSTALLED_APPS = (\r\n        ...\r\n        'realtime_validation',\r\n    )\r\n\r\n\r\n*forms.py*\r\n\r\n    from realtime_validation.forms import RealtimeValidatingModelForm\r\n  \r\n    class PersonForm(RealtimeValidatingModelForm):\r\n        class Meta:\r\n            model = Person\r\n\r\n\r\n*template.html*\r\n\r\n    ...\r\n    <script src=\"{{ STATIC_URL }}/js/realtime_validation.js\"></script>\r\n    <link href=\"{{ STATIC_URL }}/css/realtime_validation.css\" rel=\"stylesheet\">\r\n    ...\r\n    \r\n\r\n**Thats it!** As you type into the fields they will turn red when invalid characters are typed.\r\n\r\nTodo\r\n----\r\n\r\n* Only ModelForms are currently supported -- need to add code for regular forms\r\n* Only 3 types of reatlime validation are currently supported - IntegerFields, FloatFields, and *required* fields\r\n* Plans to support custom validator functions\r\n* May add descriptive error messages in realtime\r\n","google":"","note":"Don't delete this file! It's used internally to help with page regeneration."}